{
  "year": -1083,
  "year_label": "1083 BCE",
  "era_context": "Iron Age I; Late Bronze Age collapse aftermath. Ramesses III's reign in Egypt; Phoenician city-states consolidating maritime trade; early Iron Age settlement patterns established in the Levant and Aegean. Shang Dynasty in its final decades in China (traditional Zhou conquest date: 1046 BCE). Vedic period in South Asia.",
  "documentation_level": "sparse",
  "geographic_coverage_gaps": [
    "Sub-Saharan Africa",
    "Northern Europe",
    "Mesoamerica",
    "Pacific Islands",
    "Central Asia",
    "East Asia (limited year-specific documentation)"
  ],
  "events": [],
  "disconfirming_evidence": "No specific events are known for 1083 BCE.",
  "historiographic_note": "1083 BCE is not marked by any documented events in surviving sources. This is consistent with the general sparsity of year-by-year documentation for the ancient world outside of Egypt and a few other well-documented regions. The historical record is not continuous at this granularity.",
  "graph_edges": []
}