{
  "year": -1509,
  "year_label": "1510 BCE",
  "era_context": "Late Bronze Age, mid-second millennium BCE. Thutmose I is in the early-to-middle years of his reign in Egypt. The Hittite Old Kingdom is active. Mycenaean palace culture is developing in Greece. The Shang Dynasty continues in China. This is an era of territorial states, bureaucratic administration, and inter-regional trade networks.",
  "documentation_level": "minimal",
  "geographic_coverage_gaps": [
    "Sub-Saharan Africa",
    "Southeast Asia",
    "The Americas",
    "Northern Europe",
    "Central Asia",
    "Most regions outside Egypt and the Hittite heartland"
  ],
  "events": [],
  "disconfirming_evidence": "No specific events are attested for this year in any known source.",
  "historiographic_note": "This year has no documented events in surviving sources. The historical record for the mid-second millennium BCE is extremely sparse. Year-by-year documentation is not achievable for most of the world during this period. The surviving written record is heavily concentrated in Egypt and the Hittite heartland, and even there, most individual years are not recorded. Archaeological evidence provides broader context but rarely allows precise dating to specific years. The absence of recorded events reflects the limitations of the surviving record, not the absence of historical activity.",
  "graph_edges": []
}