{
  "year": -1834,
  "year_label": "1835 BCE",
  "era_context": "Middle Bronze Age; 12th Dynasty Egypt under Amenemhat III; Old Babylonian period in Mesopotamia; mature Indus Valley Civilization. This period is characterized by palace-centered administration, extensive trade networks, and relative political stability in the Near East. Egypt's 12th Dynasty represents the apex of the Middle Kingdom, with strong central authority and ambitious building programs.",
  "documentation_level": "sparse",
  "geographic_coverage_gaps": [
    "Sub-Saharan Africa",
    "Northern Europe",
    "Oceania",
    "Mesoamerica",
    "East Asia"
  ],
  "events": [],
  "disconfirming_evidence": "No disconfirming evidence identified for events listed.",
  "historiographic_note": "No specific events are attested for 1835 BCE in surviving sources. Like the surrounding years, this year falls within a period for which year-by-year documentation does not exist. The historical record for the Middle Bronze Age is characterized by the recording of major events (reigns, military campaigns, construction projects) rather than annalistic year-by-year accounts. Most years leave no trace in surviving sources, reflecting both the limitations of ancient record-keeping and the loss of written materials over millennia.",
  "graph_edges": []
}