{
  "year": -2649,
  "year_label": "2649 BCE",
  "era_context": "Egypt's Old Kingdom, Dynasty IV. Mesopotamia in the pre-Akkadian or early Akkadian period. Indus Valley Civilization in mature phase. This period represents the height of Old Kingdom Egyptian civilization.",
  "documentation_level": "minimal",
  "geographic_coverage_gaps": [
    "Sub-Saharan Africa",
    "Southeast Asia",
    "Mesoamerica",
    "Northern Europe",
    "Mesopotamia",
    "Central Asia",
    "East Asia"
  ],
  "events": [],
  "disconfirming_evidence": "No specific events are documented for 2649 BCE in any surviving source tradition.",
  "historiographic_note": "For 2649 BCE, documentation is negligible. No contemporary written records survive. All knowledge of this period derives from archaeological evidence and later compilations. The year is a modern calendrical construct with no historical events that can be documented.",
  "graph_edges": []
}