{
  "year": -2640,
  "year_label": "2640 BCE",
  "era_context": "Egypt's Old Kingdom, Dynasty IV, during Khufu's reign (c. 2589\u20132566 BCE). The Great Pyramid of Giza was recently completed. Mesopotamia remained in the Early Dynastic III period with competing city-states. The Indus Valley Civilization was developing urban centers. No major documented events are known for this specific year.",
  "documentation_level": "negligible",
  "geographic_coverage_gaps": [
    "Mesopotamia",
    "Indus Valley",
    "Sub-Saharan Africa",
    "East Asia",
    "The Americas",
    "Egypt (no specific events recorded for this year)"
  ],
  "events": [],
  "disconfirming_evidence": "No disconfirming evidence identified for events listed.",
  "historiographic_note": "2640 BCE is not marked by any known documented historical events in surviving sources. This year falls within Khufu's reign, a period of Egyptian prosperity and monumental construction, but no specific events are recorded for this year. The historical record for the Old Kingdom is sparse in textual detail; most knowledge derives from archaeological evidence. The silence of sources for this year is typical of the period and does not indicate historical inactivity.",
  "graph_edges": []
}