{
  "year": -3164,
  "year_label": "3164 BCE",
  "era_context": "Early Bronze Age. Egypt is in the Predynastic or earliest Early Dynastic period. Mesopotamian city-states are developing complex societies with early writing. The Indus Valley Civilization is emerging. This period marks the transition from prehistory to history in some regions, though written records are extremely sparse.",
  "documentation_level": "negligible",
  "geographic_coverage_gaps": [
    "All regions except Egypt and Mesopotamia have virtually no year-specific documentation",
    "Sub-Saharan Africa",
    "East Asia",
    "Oceania",
    "The Americas",
    "Northern Europe and the Steppe"
  ],
  "events": [],
  "disconfirming_evidence": "No disconfirming evidence identified for events listed.",
  "historiographic_note": "No specific events are attested for this year. Year-by-year historical documentation does not exist for this period. The historical record is limited to broad chronological frameworks (which are themselves uncertain and subject to revision), king lists compiled centuries or millennia later, and archaeological evidence that cannot be resolved to individual years. The concept of 'history' in the modern sense\u2014documented, datable events\u2014does not apply to this year. Any claim to specific events would be speculation or fabrication.",
  "graph_edges": []
}