{
  "year": -543,
  "year_label": "543 BCE",
  "era_context": "The mid-6th century BCE under Cyrus II in Persia, the Spring and Autumn period in China, and the Axial Age across multiple civilisations. This year falls within the period of Persian imperial consolidation and continued intellectual and religious ferment in Greece, India, and China.",
  "documentation_level": "minimal",
  "geographic_coverage_gaps": [
    "Sub-Saharan Africa (minimal written sources)",
    "Northern Europe (no contemporary documentation)",
    "Pre-Columbian Americas (no written records)",
    "Southeast Asia (sparse archaeological evidence)",
    "Most of the Indian subcontinent outside major kingdoms",
    "Most of China outside the major states"
  ],
  "events": [],
  "disconfirming_evidence": "No events identified for this year. No disconfirming evidence to report.",
  "historiographic_note": "This year is essentially undocumented in surviving historical sources. No contemporary records, inscriptions, chronicles, or primary texts are known to date specifically to 543 BCE. The historical record for this year is a complete blank. Any attempt to describe specific events would be speculation or inference from broader period narratives. This is not unusual for ancient years; the further back in time we go, the sparser the documentation becomes. Archaeological evidence cannot be precisely dated to individual years in this period.",
  "graph_edges": []
}